{
    "outputs": [
        {
            "created_at": "2018-08-16T21:18:29.053333953Z",
            "data": {
                "concepts": [
                    {
                        "app_id": "main",
                        "id": "ai_786Zr311",
                        "name": "no person",
                        "value": 0.97085893
                    },
                    {
                        "app_id": "main",
                        "id": "ai_LplXDDZ2",
                        "name": "car",
                        "value": 0.9705261
                    },
                    {
                        "app_id": "main",
                        "id": "ai_WTrlNkqM",
                        "name": "vehicle",
                        "value": 0.9636948
                    },
                    {
                        "app_id": "main",
                        "id": "ai_Xxjc3MhT",
                        "name": "transportation system",
                        "value": 0.96193784
                    },
                    {
                        "app_id": "main",
                        "id": "ai_1p2zMmqb",
                        "name": "retro",
                        "value": 0.91895896
                    },
                    {
                        "app_id": "main",
                        "id": "ai_VRmbGVWh",
                        "name": "travel",
                        "value": 0.8321333
                    },
                    {
                        "app_id": "main",
                        "id": "ai_gJm9b4ts",
                        "name": "vintage",
                        "value": 0.8064287
                    },
                    {
                        "app_id": "main",
                        "id": "ai_Zmhsv0Ch",
                        "name": "outdoors",
                        "value": 0.8045135
                    },
                    {
                        "app_id": "main",
                        "id": "ai_SVshtN54",
                        "name": "one",
                        "value": 0.7975409
                    },
                    {
                        "app_id": "main",
                        "id": "ai_TZ3C79C6",
                        "name": "road",
                        "value": 0.79217744
                    },
                    {
                        "app_id": "main",
                        "id": "ai_lNsKfmXb",
                        "name": "sky",
                        "value": 0.76474667
                    },
                    {
                        "app_id": "main",
                        "id": "ai_S0rvLGPz",
                        "name": "old",
                        "value": 0.7525184
                    },
                    {
                        "app_id": "main",
                        "id": "ai_n9vjC1jB",
                        "name": "light",
                        "value": 0.7457148
                    },
                    {
                        "app_id": "main",
                        "id": "ai_9MHSc8T5",
                        "name": "classic",
                        "value": 0.74009335
                    },
                    {
                        "app_id": "main",
                        "id": "ai_l2vWw8mr",
                        "name": "empty",
                        "value": 0.7285182
                    },
                    {
                        "app_id": "main",
                        "id": "ai_l8TKp2h5",
                        "name": "people",
                        "value": 0.70739603
                    },
                    {
                        "app_id": "main",
                        "id": "ai_tr0MBp64",
                        "name": "traffic",
                        "value": 0.70722175
                    },
                    {
                        "app_id": "main",
                        "id": "ai_GjVpxXrs",
                        "name": "street",
                        "value": 0.69294333
                    },
                    {
                        "app_id": "main",
                        "id": "ai_cB1DJqcV",
                        "name": "dirty",
                        "value": 0.6892681
                    },
                    {
                        "app_id": "main",
                        "id": "ai_4WQx8fHH",
                        "name": "asphalt",
                        "value": 0.67030454
                    }
                ]
            },
            "id": "97d3468846bd4f07aa222b5907d04cf4",
            "input": {
                "data": {
                    "image": {
                        "base64": "dHJ1ZQ==",
                        "url": "https://s3.amazonaws.com/clarifai-api/img3/prod/small/0794b023355445138f58a119e09ab111/f6835c815eb2aa83d532afb3c379a4dd"
                    }
                },
                "id": "a7d7712ad5c0455fa28e44a1292c9f02"
            },
            "model": {
                "app_id": "main",
                "created_at": "2016-03-09T17:11:39.608845Z",
                "display_name": "General",
                "id": "aaa03c23b3724a16a56b629203edc62c",
                "model_version": {
                    "created_at": "2016-07-13T01:19:12.147644Z",
                    "id": "aa9ca48295b37401f8af92ad1af0d91d",
                    "status": {
                        "code": 21100,
                        "description": "Model trained successfully"
                    }
                },
                "name": "general-v1.3",
                "output_info": {
                    "message": "Show output_info with: GET /models/{model_id}/output_info",
                    "type": "concept",
                    "type_ext": "concept"
                }
            },
            "status": {
                "code": 10000,
                "description": "Ok"
            }
        }
    ],
    "response_time": 1.1783530712127686,
    "status": {
        "code": 10000,
        "description": "Ok"
    }
}